atmosphere_gost/__init__.py
atmosphere_gost/atmosphere_GOST4401_81.py
atmosphere_gost-0.2.3.dist-info/LICENSE
atmosphere_gost-0.2.3.dist-info/METADATA
atmosphere_gost-0.2.3.dist-info/WHEEL
atmosphere_gost-0.2.3.dist-info/top_level.txt
atmosphere_gost-0.2.3.dist-info/RECORD
