Metadata-Version: 2.1
Name: atmosphere_gost
Version: 0.2.3
Summary: Standard Atmosphere, GOST 4401-81
Author-email: "Pavel V. Chuvakhov" <pavel.chuvakhov@yandex.ru>
Project-URL: Homepage, https://github.com/0x13b/atmosphere_gost/
Project-URL: Repository, https://github.com/0x13b/atmosphere_gost.git
Keywords: atmosphere,pressure,temperature,gost,standard,physics
Classifier: Development Status :: 4 - Beta
Classifier: Programming Language :: Python :: 3
Classifier: Programming Language :: Python :: 3.9
Classifier: License :: OSI Approved :: MIT License
Classifier: Operating System :: OS Independent
Classifier: Intended Audience :: Education
Classifier: Intended Audience :: Science/Research
Classifier: Natural Language :: Russian
Classifier: Topic :: Scientific/Engineering
Classifier: Topic :: Scientific/Engineering :: Physics
Classifier: Topic :: Scientific/Engineering :: Atmospheric Science
Requires-Python: >=3.9
License-File: LICENSE
